[
  {
    "operatorAddress": "injvaloper15gnk95hvqrsr343ecqjuv7yf2af9rkdqwmn3tf",
    "jailed": false,
    "consensusPubKey": "zj4nhcZuJlef6ILbe2gLtO5oxRL2QDfSt4F+Ufraqsk=",
    "status": "Bonded",
    "tokens": "1100",
    "delegatorShares": "1100000000000000000000",
    "description": {
      "moniker": "n0",
      "identity": "E83C7B8E58DC11E0",
      "website": "",
      "securityContact": "",
      "details": ""
    },
    "unbondingHeight": 0,
    "unbondingTime": 0,
    "commission": {
      "commissionRates": {
        "rate": "0.1",
        "maxRate": "0.2",
        "maxChangeRate": "0.01"
      },
      "updateTime": "2026-06-15T14:59:38.346Z"
    },
    "minSelfDelegation": "1",
    "valconsAddress": "injvalcons1nueqseemsut7jswv964579qvdhpulxuu8kfjk2"
  },
  {
    "operatorAddress": "injvaloper1lrr6tf29yjz4q8ewjgcd4sjj97mh9xy9cdplrn",
    "jailed": false,
    "consensusPubKey": "vOVcsDGqPmTaBLNa2PpbmHoCvOs7jo58QLd1jk1qkyo=",
    "status": "Bonded",
    "tokens": "1000",
    "delegatorShares": "1000000000000000000000",
    "description": {
      "moniker": "n2",
      "identity": "E83C7B8E58DC11E1",
      "website": "",
      "securityContact": "",
      "details": ""
    },
    "unbondingHeight": 0,
    "unbondingTime": 0,
    "commission": {
      "commissionRates": {
        "rate": "0.1",
        "maxRate": "0.2",
        "maxChangeRate": "0.01"
      },
      "updateTime": "2026-06-15T14:59:38.346Z"
    },
    "minSelfDelegation": "1",
    "valconsAddress": "injvalcons19uuv4r9x9t8twu8yhvku0dx68dzjsa83dctgfx"
  },
  {
    "operatorAddress": "injvaloper1q8nh58utz78ree7e4cnxnvmyt0mrq5wwxfth3j",
    "jailed": false,
    "consensusPubKey": "0kmJJQkUGeBrO3Y1+9gSPIyiZp6P23qa2NykRDDwq60=",
    "status": "Bonded",
    "tokens": "100",
    "delegatorShares": "100000000000000000000",
    "description": {
      "moniker": "n1",
      "identity": "",
      "website": "",
      "securityContact": "",
      "details": ""
    },
    "unbondingHeight": 0,
    "unbondingTime": 0,
    "commission": {
      "commissionRates": {
        "rate": "0.1",
        "maxRate": "0.2",
        "maxChangeRate": "0.01"
      },
      "updateTime": "2026-06-15T14:59:38.346Z"
    },
    "minSelfDelegation": "1",
    "valconsAddress": "injvalcons1gw9s2wneeymj82lp7ctkwpvpsfeap2fzz2yjpp"
  }
]