[
  {
    "operatorAddress": "injvaloper15gnk95hvqrsr343ecqjuv7yf2af9rkdqwmn3tf",
    "jailed": false,
    "consensusPubKey": "QMzl/tV4uQWuj7OfNw5jSYIn0tLeCRsdrJ0JCcqIQOM=",
    "status": "Bonded",
    "tokens": "1100",
    "delegatorShares": "1100000000000000000000",
    "description": {
      "moniker": "n0",
      "identity": "E83C7B8E58DC11E0",
      "website": "",
      "securityContact": "",
      "details": ""
    },
    "unbondingHeight": 0,
    "unbondingTime": 0,
    "commission": {
      "commissionRates": {
        "rate": "0.1",
        "maxRate": "0.2",
        "maxChangeRate": "0.01"
      },
      "updateTime": "2026-03-24T10:10:43.167Z"
    },
    "minSelfDelegation": "1",
    "valconsAddress": "injvalcons1r73mssnlaa9xsmjc0cde5dp9p8eqrg3wgpf6lh"
  },
  {
    "operatorAddress": "injvaloper1lrr6tf29yjz4q8ewjgcd4sjj97mh9xy9cdplrn",
    "jailed": false,
    "consensusPubKey": "9P3uB5Mukgyip8JxE5UxIqgZGkRD3V1y4qAZGVsroxQ=",
    "status": "Bonded",
    "tokens": "1000",
    "delegatorShares": "1000000000000000000000",
    "description": {
      "moniker": "n2",
      "identity": "E83C7B8E58DC11E1",
      "website": "",
      "securityContact": "",
      "details": ""
    },
    "unbondingHeight": 0,
    "unbondingTime": 0,
    "commission": {
      "commissionRates": {
        "rate": "0.1",
        "maxRate": "0.2",
        "maxChangeRate": "0.01"
      },
      "updateTime": "2026-03-24T10:10:43.167Z"
    },
    "minSelfDelegation": "1",
    "valconsAddress": "injvalcons1e8caj8jjvnrsqcswqp8nu900wa8snvde5hyzda"
  },
  {
    "operatorAddress": "injvaloper1q8nh58utz78ree7e4cnxnvmyt0mrq5wwxfth3j",
    "jailed": false,
    "consensusPubKey": "ISeDJ9juR90moOTnc/84HltSCDiVJclG/VFQ2qbH7aY=",
    "status": "Bonded",
    "tokens": "100",
    "delegatorShares": "100000000000000000000",
    "description": {
      "moniker": "n1",
      "identity": "",
      "website": "",
      "securityContact": "",
      "details": ""
    },
    "unbondingHeight": 0,
    "unbondingTime": 0,
    "commission": {
      "commissionRates": {
        "rate": "0.1",
        "maxRate": "0.2",
        "maxChangeRate": "0.01"
      },
      "updateTime": "2026-03-24T10:10:43.167Z"
    },
    "minSelfDelegation": "1",
    "valconsAddress": "injvalcons154pczupre4vqlzearl7z9px2u7czx7zype24aj"
  }
]