[
  {
    "operatorAddress": "injvaloper15gnk95hvqrsr343ecqjuv7yf2af9rkdqwmn3tf",
    "jailed": false,
    "consensusPubKey": "2MT7pRoNuOmq3vo5k5l+G3DIb9AXYhzApAfgSbb2Iws=",
    "status": "Bonded",
    "tokens": "1100",
    "delegatorShares": "1100000000000000000000",
    "description": {
      "moniker": "n0",
      "identity": "E83C7B8E58DC11E0",
      "website": "",
      "securityContact": "",
      "details": ""
    },
    "unbondingHeight": 0,
    "unbondingTime": 0,
    "commission": {
      "commissionRates": {
        "rate": "0.1",
        "maxRate": "0.2",
        "maxChangeRate": "0.01"
      },
      "updateTime": "2026-03-18T10:35:55.549Z"
    },
    "minSelfDelegation": "1",
    "valconsAddress": "injvalcons1af6ve048mx4qx75ykp2mye5gdt2r4daugkdh3k"
  },
  {
    "operatorAddress": "injvaloper1lrr6tf29yjz4q8ewjgcd4sjj97mh9xy9cdplrn",
    "jailed": false,
    "consensusPubKey": "VB53QRYAY4YzOfGE9kq4n0703pZQ9GOStPzy9LWIDfA=",
    "status": "Bonded",
    "tokens": "1000",
    "delegatorShares": "1000000000000000000000",
    "description": {
      "moniker": "n2",
      "identity": "E83C7B8E58DC11E1",
      "website": "",
      "securityContact": "",
      "details": ""
    },
    "unbondingHeight": 0,
    "unbondingTime": 0,
    "commission": {
      "commissionRates": {
        "rate": "0.1",
        "maxRate": "0.2",
        "maxChangeRate": "0.01"
      },
      "updateTime": "2026-03-18T10:35:55.549Z"
    },
    "minSelfDelegation": "1",
    "valconsAddress": "injvalcons1wc73jhnyqv68j928xp0vx72nxgyqy3227typfe"
  },
  {
    "operatorAddress": "injvaloper1q8nh58utz78ree7e4cnxnvmyt0mrq5wwxfth3j",
    "jailed": false,
    "consensusPubKey": "xTHq4YE+JymeUes02VzLswh96/TfjTZvvAYLF9OkxGg=",
    "status": "Bonded",
    "tokens": "100",
    "delegatorShares": "100000000000000000000",
    "description": {
      "moniker": "n1",
      "identity": "",
      "website": "",
      "securityContact": "",
      "details": ""
    },
    "unbondingHeight": 0,
    "unbondingTime": 0,
    "commission": {
      "commissionRates": {
        "rate": "0.1",
        "maxRate": "0.2",
        "maxChangeRate": "0.01"
      },
      "updateTime": "2026-03-18T10:35:55.549Z"
    },
    "minSelfDelegation": "1",
    "valconsAddress": "injvalcons17jnrrw690hukvm95slh83efjdf5adld9ywkn5r"
  }
]